[
  {
    "errata_id": 6896,
    "doc-id": "RFC1503",
    "errata_status_code": "Reported",
    "errata_type_code": "Technical",
    "section": 1503,
    "orig_text": "801.2 in the text well you took me to parcel.",
    "correct_text": "In the business part of 801.2 in parcel even after the 2017 parcel meeting they wouldn’t let me represent myself in or the 2015. ",
    "notes": "Well I can talk about this more in person and I do know everything we do need to talk about. It will just take time to get through the case that needs to be worked through",
    "submit_date": "2022-03-25",
    "submitter_name": "Jesus m Alvarado",
    "verifier_id": 99,
    "verifier_name": null,
    "update_date": null
  }
]
