[
  {
    "errata_id": 507,
    "doc-id": "RFC2046",
    "errata_status_code": "Verified",
    "errata_type_code": "Technical",
    "section": "5.1.5",
    "orig_text": "      Date: Mon, 22 Mar 1994 13:34:51 +0000",
    "correct_text": "      Date: Tue, 22 Mar 1994 13:34:51 +0000 ",
    "notes": "",
    "submit_date": "2003-10-04",
    "submitter_name": "Bruce Lilly",
    "verifier_id": 99,
    "verifier_name": null,
    "update_date": "2019-09-10 09:09:03"
  },
  {
    "errata_id": 508,
    "doc-id": "RFC2046",
    "errata_status_code": "Verified",
    "errata_type_code": "Technical",
    "section": "99Appendix A states: ",
    "orig_text": "     discard-text := *(*text CRLF)",
    "correct_text": "     discard-text := *(*text CRLF) *text\n",
    "notes": "",
    "submit_date": "2001-10-04",
    "submitter_name": "Herman Meerlo",
    "verifier_id": 99,
    "verifier_name": null,
    "update_date": "2019-09-10 09:09:03"
  },
  {
    "errata_id": 509,
    "doc-id": "RFC2046",
    "errata_status_code": "Verified",
    "errata_type_code": "Editorial",
    "section": 9,
    "orig_text": "9.  Security Considerations",
    "correct_text": "8.  Security Considerations",
    "notes": "In the Table of Contents, the Security Considerations is listed to be in Section 8.  However, in the text, both the Security Considerations and Authors' Addresses are in Section 9; there is no Section 8.\r\n\r\n",
    "submit_date": "2004-02-03",
    "submitter_name": "Steve Bellovin",
    "verifier_id": 99,
    "verifier_name": null,
    "update_date": "2019-09-10 09:09:03"
  },
  {
    "errata_id": 510,
    "doc-id": "RFC2046",
    "errata_status_code": "Verified",
    "errata_type_code": "Editorial",
    "section": "5.1.5",
    "orig_text": "undesireble \r\n\r\nseperate",
    "correct_text": "undesirable\r\n\r\nseparate",
    "notes": "Spelling errors.",
    "submit_date": "2001-12-22",
    "submitter_name": "Bruce Lilly",
    "verifier_id": 99,
    "verifier_name": null,
    "update_date": "2019-09-10 09:09:03"
  },
  {
    "errata_id": 511,
    "doc-id": "RFC2046",
    "errata_status_code": "Verified",
    "errata_type_code": "Editorial",
    "section": 3,
    "orig_text": "    (2)   image -- image data.  \"Image\" requires a display device\r\n          (such as a graphical display, a graphics printer, or a\r\n          FAX machine) to view the information. An initial\r\n          subtype is defined for the widely-used image format\r\n          JPEG. .  subtypes are defined for two widely-used image\r\n          formats, jpeg and gif.",
    "correct_text": "    (2)   image -- image data.  \"Image\" requires a display device\r\n          (such as a graphical display, a graphics printer, or a\r\n          FAX machine) to view the information. Subtypes are defined\r\n          for two widely-used image formats, jpeg and gif.\r\n",
    "notes": "The sentence previous to the last should be deleted, as it is covered by the last sentence.\r\n\r\n",
    "submit_date": "2005-01-06",
    "submitter_name": "Lars Kasper",
    "verifier_id": 116,
    "verifier_name": "Alexey Melnikov",
    "update_date": "2019-09-10 09:09:03"
  },
  {
    "errata_id": 588,
    "doc-id": "RFC2046",
    "errata_status_code": "Verified",
    "errata_type_code": "Technical",
    "section": "5.2.2.2",
    "orig_text": "Date: Fri, 26 Mar 1993 12:59:38 -0500 (EST)\r\nSubject: Audio mail\r\nMessage-ID: <anotherid@foo.com>",
    "correct_text": "Date: Fri, 26 Mar 1993 12:59:38 -0500 (EST)\r\nMessage-ID: <anotherid@foo.com>\r\nSubject: Audio mail",
    "notes": "",
    "submit_date": "2001-12-22",
    "submitter_name": "Bruce Lilly",
    "verifier_id": 99,
    "verifier_name": null,
    "update_date": "2019-09-10 09:09:03"
  },
  {
    "errata_id": 589,
    "doc-id": "RFC2046",
    "errata_status_code": "Verified",
    "errata_type_code": "Technical",
    "section": "5.2.3.7",
    "orig_text": "Content-Type: message/external-body;\r\n              access-type=mail-server\r\n              server=\"listserv@bogus.bitnet\";\r\n              expiration=\"Fri, 14 Jun 1991 19:13:14 -0400 (EDT)\"",
    "correct_text": "Content-Type: message/external-body;\r\n              access-type=mail-server;\r\n              server=\"listserv@bogus.bitnet\";\r\n              expiration=\"Fri, 14 Jun 1991 19:13:14 -0400 (EDT)\"",
    "notes": "Semicolons were missing.",
    "submit_date": "2001-12-22",
    "submitter_name": "Bruce Lilly",
    "verifier_id": 99,
    "verifier_name": null,
    "update_date": "2019-09-10 09:09:03"
  },
  {
    "errata_id": 4609,
    "doc-id": "RFC2046",
    "errata_status_code": "Held for Document Update",
    "errata_type_code": "Editorial",
    "section": 3,
    "orig_text": "          particular, formats that employ embeddded binary\r\n",
    "correct_text": "          particular, formats that employ embedded binary\r\n",
    "notes": "\"embeddded\" has triple \"d\".",
    "submit_date": "2016-02-01",
    "submitter_name": "Oleg Andriyanov",
    "verifier_id": 130,
    "verifier_name": "Barry Leiba",
    "update_date": "2019-09-10 09:09:03"
  },
  {
    "errata_id": 6582,
    "doc-id": "RFC2046",
    "errata_status_code": "Reported",
    "errata_type_code": "Editorial",
    "section": "4.1.4",
    "orig_text": "Unrecognized subtypes which also specify an unrecognized charset should be treated as \"application/octet- stream\".",
    "correct_text": "Unrecognized subtypes which also specify an unrecognized charset should be treated as \"application/octet-stream\".",
    "notes": "Space looks like a typo.",
    "submit_date": "2021-05-15",
    "submitter_name": "ojab",
    "verifier_id": 99,
    "verifier_name": null,
    "update_date": null
  },
  {
    "errata_id": 6583,
    "doc-id": "RFC2046",
    "errata_status_code": "Reported",
    "errata_type_code": "Editorial",
    "section": "5.1.2",
    "orig_text": "It is essential that such entities be handled correctly when they are themselves imbedded inside of another \"multipart\" structure.",
    "correct_text": "It is essential that such entities be handled correctly when they are themselves embedded inside of another \"multipart\" structure.",
    "notes": "`imbedded` is a typo",
    "submit_date": "2021-05-15",
    "submitter_name": "ojab",
    "verifier_id": 99,
    "verifier_name": null,
    "update_date": null
  },
  {
    "errata_id": 6776,
    "doc-id": "RFC2046",
    "errata_status_code": "Reported",
    "errata_type_code": "Editorial",
    "section": "5.1.1",
    "orig_text": "NOTE:  The CRLF preceding the boundary delimiter line is conceptually\r\n   attached to the boundary so that it is possible to have a part that\r\n   does not end with a CRLF (line  break).  Body parts that must be\r\n   considered to end with line breaks, therefore, must have two CRLFs\r\n   preceding the boundary delimiter line, the first of which is part of\r\n   the preceding body part, and the second of which is part of the\r\n   encapsulation boundary.",
    "correct_text": "NOTE:  The CRLF preceding the boundary delimiter line is conceptually\r\n   attached to the boundary so that it is possible to have a part that\r\n   does not end with a CRLF (line  break).  Body parts that must be\r\n   considered to end with line breaks, therefore, must have two CRLFs\r\n   preceding the boundary delimiter line, the first of which is part of\r\n   the preceding body part, and the second of which is part of the\r\n   encapsulation boundary.\r\n\r\nThe requirement that the encapsulation boundary begins  with\r\na  CRLF  implies  that  the  body of a multipart entity must\r\nitself begin with a CRLF before the first encapsulation line\r\n--  that  is, if the \"preamble\" area is not used, the entity\r\nheaders must be followed by TWO CRLFs.  This is  indeed  how\r\nsuch  entities  should be composed.  A tolerant mail reading\r\nprogram, however, may interpret a  body  of  type  multipart\r\nthat  begins  with  an encapsulation line NOT initiated by a\r\nCRLF  as  also  being  an  encapsulation  boundary,  but   a\r\ncompliant  mail  sending  program  must  not  generate  such\r\nentities.",
    "notes": "Recommend re-introducing the wording from the original RFC (1341) regarding preceding CRLF and the first delimiter line. Current RFC is ambiguous about handling the initial line without it.",
    "submit_date": "2021-12-05",
    "submitter_name": "Brian Antos",
    "verifier_id": 99,
    "verifier_name": null,
    "update_date": null
  },
  {
    "errata_id": 6800,
    "doc-id": "RFC2046",
    "errata_status_code": "Reported",
    "errata_type_code": "Technical",
    "section": "5.1.4",
    "orig_text": "                                    In the case where one of the\r\n   alternatives is itself of type \"multipart\" and contains unrecognized\r\n   sub-parts, the user agent may choose either to show that alternative,\r\n   an earlier alternative, or both.\r\n\r\n",
    "correct_text": "                                    In the case where one of the\r\n   alternatives is itself of type \"multipart\" and contains unrecognized\r\n   sub-parts, the user agent may choose to either show that alternative,\r\n   show an earlier alternative, or let the user choose which alternative\r\n   to show.\r\n",
    "notes": "The quoted sentence conflicts with the following sentence later in the same section:\r\n\r\n                  What is most critical, however, is that the user not\r\n   automatically be shown multiple versions of the same data.  Either\r\n   the user should be shown the last recognized version or should be\r\n   given the choice.\r\n\r\nI assume the correction should be as proposed, but other options are conceivable.",
    "submit_date": "2021-12-27",
    "submitter_name": "Daniel Shahaf",
    "verifier_id": 99,
    "verifier_name": null,
    "update_date": null
  }
]
