[
  {
    "errata_id": "7605",
    "doc-id": "RFC4645",
    "errata_status_code": "Rejected",
    "errata_type_code": "Technical",
    "section": "3",
    "orig_text": "The IANA language subtag registry can be found at\r\n   <http://www.iana.org/numbers.html> under \"Language Tags\".",
    "correct_text": "The IANA language subtag registry can be found at\r\n   <https://www.iana.org/protocols> under \"Language Tags\", or\r\n    <https://www.iana.org/assignments/language-tags/language-tags.xhtml>",
    "notes": "Language tags and sub tags are obsolete\n --VERIFIER NOTES-- \n   The current text was correct at the time of writing, and is still correct (with the redirect).",
    "submit_date": "2023-08-16",
    "submitter_name": "Timothy McSweeney",
    "verifier_id": "170",
    "verifier_name": "Francesca Palombini",
    "update_date": "2024-05-13 04:12:21"
  }
]
