[
  {
    "errata_id": "3194",
    "doc-id": "RFC5865",
    "errata_status_code": "Held for Document Update",
    "errata_type_code": "Editorial",
    "section": "2.2",
    "orig_text": "   There are at least six major ways that capacity admission is done or\r\n   has been proposed to be done for real-time applications.  Each will\r\n   be described below, and Section 3 will judge which ones are likely to\r\n   meet the requirements of the Admitted Telephony service class.  These\r\n   include:\r\n",
    "correct_text": "   There are at least six major ways that capacity admission is done or\r\n   has been proposed to be done for real-time applications.  Each will\r\n   be described below, and Section 2.3 will judge which ones are likely to\r\n   meet the requirements of the Admitted Telephony service class.  These\r\n   include:\r\n",
    "notes": "Section 2.3 is the one, which recommends capacity admission procedures, while Section 3 summarizes proposed changes.",
    "submit_date": "2012-04-17",
    "submitter_name": "Sergey Antipov",
    "verifier_id": "129",
    "verifier_name": "Wesley Eddy",
    "update_date": "2019-09-10 09:09:03"
  }
]
