[
  {
    "errata_id": "3203",
    "doc-id": "RFC6488",
    "errata_status_code": "Held for Document Update",
    "errata_type_code": "Editorial",
    "section": "Table of Con",
    "orig_text": "                  2.1.6.7. unsigneAttrs ...............................8",
    "correct_text": "                  2.1.6.7. unsignedAttrs ..............................8",
    "notes": null,
    "submit_date": "2012-04-26",
    "submitter_name": "David Mandelberg",
    "verifier_id": "122",
    "verifier_name": "Stewart Bryant",
    "update_date": "2019-09-10 09:09:03"
  }
]
