[
  {
    "errata_id": 6732,
    "doc-id": "RFC7285",
    "errata_status_code": "Reported",
    "errata_type_code": "Editorial",
    "section": "15.3.2",
    "orig_text": "HTTP Digestion Authentication",
    "correct_text": "HTTP Digest Authentication",
    "notes": "I'm classifying this as editorial because the correction is so obvious; feel free to reclassify it.",
    "submit_date": "2021-11-06",
    "submitter_name": "Samuel Weiler",
    "verifier_id": 99,
    "verifier_name": null,
    "update_date": null
  }
]
